crono_api_client/__init__.py
crono_api_client/api.py
crono_api_client/job.py
crono_api_client/triggers.py
crono_api_client-0.1.17.dist-info/LICENSE
crono_api_client-0.1.17.dist-info/METADATA
crono_api_client-0.1.17.dist-info/WHEEL
crono_api_client-0.1.17.dist-info/top_level.txt
crono_api_client-0.1.17.dist-info/RECORD
